django_tools/__init__.py
django_tools/apps.py
django_tools/checks.py
django_tools/constants.py
django_tools/context_managers.py
django_tools/context_processors.py
django_tools/decorators.py
django_tools/exception_plus.py
django_tools/exceptions.py
django_tools/forms_utils.py
django_tools/limit_to_usergroups.py
django_tools/model_utils.py
django_tools/models.py
django_tools/permissions.py
django_tools/settings_utils.py
django_tools/validators.py
django_tools/admin_tools/__init__.py
django_tools/admin_tools/test_generator.py
django_tools/auto_update_cache/README.creole
django_tools/auto_update_cache/__init__.py
django_tools/auto_update_cache/filebased.py
django_tools/cache/README.creole
django_tools/cache/__init__.py
django_tools/cache/site_cache_middleware.py
django_tools/cache/smooth_cache_backends.py
django_tools/debug/README.creole
django_tools/debug/__init__.py
django_tools/debug/delay.py
django_tools/debug/middlewares.py
django_tools/fields/__init__.py
django_tools/fields/directory.py
django_tools/fields/language_code.py
django_tools/fields/media_path.py
django_tools/fields/sign_separated.py
django_tools/fields/static_path.py
django_tools/fields/url.py
django_tools/fields/tests/__init__.py
django_tools/fields/tests/test_static_path.py
django_tools/file_storage/__init__.py
django_tools/file_storage/file_system_storage.py
django_tools/filemanager/README.creole
django_tools/filemanager/__init__.py
django_tools/filemanager/exceptions.py
django_tools/filemanager/filemanager.py
django_tools/filemanager/filesystem_browser.py
django_tools/filemanager/tests.py
django_tools/filemanager/utils.py
django_tools/fixture_tools/__init__.py
django_tools/fixture_tools/languages.py
django_tools/local_sync_cache/LocalSyncCacheMiddleware.py
django_tools/local_sync_cache/__init__.py
django_tools/local_sync_cache/local_sync_cache.py
django_tools/log_utils/__init__.py
django_tools/log_utils/syslog_handler.py
django_tools/log_utils/throttle_admin_email_handler.py
django_tools-0.57.0.dist-info/METADATA
django_tools-0.57.0.dist-info/WHEEL
django_tools-0.57.0.dist-info/entry_points.txt
django_tools-0.57.0.dist-info/licenses/AUTHORS
django_tools-0.57.0.dist-info/licenses/LICENSE
django_tools-0.57.0.dist-info/RECORD
