Metadata-Version: 2.4
Name: django-tools
Version: 0.57.0
Summary: miscellaneous tools for Django based projects
Project-URL: Documentation, https://github.com/jedie/django-tools/
Project-URL: Source, https://github.com/jedie/django-tools/
Author-email: Jens Diemer <django-tools@jensdiemer.de>
License: GPL-3.0-or-later
License-File: AUTHORS
License-File: LICENSE
Requires-Python: >=3.11
Requires-Dist: bleach
Requires-Dist: bx-django-utils
Requires-Dist: bx-py-utils
Requires-Dist: colorlog
Requires-Dist: django
Requires-Dist: django-debug-toolbar
Requires-Dist: gunicorn
Requires-Dist: icdiff
Requires-Dist: pprintpp
